README.md
licence.txt
setup.py
gwaihir/__init__.py
gwaihir/dataset.py
gwaihir/gui.py
gwaihir/plot.py
gwaihir/version.py
gwaihir.egg-info/PKG-INFO
gwaihir.egg-info/SOURCES.txt
gwaihir.egg-info/dependency_links.txt
gwaihir.egg-info/requires.txt
gwaihir.egg-info/top_level.txt
gwaihir/controller/__init__.py
gwaihir/controller/control_data_frame.py
gwaihir/controller/control_facet.py
gwaihir/controller/control_phase_retrieval.py
gwaihir/controller/control_plot_data.py
gwaihir/controller/control_postprocess.py
gwaihir/controller/control_preprocess.py
gwaihir/controller/control_readme.py
gwaihir/controller/control_startup.py
gwaihir/scripts/job_esrf.slurm
gwaihir/scripts/plot_paraview_slices.py
gwaihir/scripts/run_init_dir.py
gwaihir/scripts/run_slurm_job.sh
gwaihir/scripts/workflow_cli.sh
gwaihir/view/__init__.py
gwaihir/view/tab_data_frame.py
gwaihir/view/tab_detector.py
gwaihir/view/tab_facet.py
gwaihir/view/tab_instrument.py
gwaihir/view/tab_phase_retrieval.py
gwaihir/view/tab_plot_data.py
gwaihir/view/tab_postprocess.py
gwaihir/view/tab_preprocess.py
gwaihir/view/tab_readme.py
gwaihir/view/tab_startup.py