Metadata-Version: 2.1
Name: gwaihir
Version: 0.0.6
Summary: Python package for BCDI data analysis
Home-page: https://github.com/DSimonne/gwaihir/tree/master
Author: David Simonne
Author-email: david.simonne@universite-paris-saclay.fr
License: UNKNOWN
Download-URL: https://pypi.org/project/gwaihir/
Keywords: BCDI,ipywidgets,PyNX
Platform: UNKNOWN
Classifier: Programming Language :: Python :: 3
Classifier: License :: OSI Approved :: GNU General Public License v3 (GPLv3)
Classifier: Operating System :: OS Independent
Requires-Python: >=3.6
